cloudmesh/common/Benchmark.py
cloudmesh/common/DateTime.py
cloudmesh/common/DictList.py
cloudmesh/common/FlatDict.py
cloudmesh/common/Host.py
cloudmesh/common/Inspector.py
cloudmesh/common/JobMultiHostScript.py
cloudmesh/common/JobScript.py
cloudmesh/common/JobSet.py
cloudmesh/common/Printer.py
cloudmesh/common/Shell.py
cloudmesh/common/StopWatch.py
cloudmesh/common/StopWatchMllog.py
cloudmesh/common/TableParser.py
cloudmesh/common/Tabulate.py
cloudmesh/common/__init__.py
cloudmesh/common/base.py
cloudmesh/common/console.py
cloudmesh/common/debug.py
cloudmesh/common/default.py
cloudmesh/common/deprecated.py
cloudmesh/common/dotdict.py
cloudmesh/common/error.py
cloudmesh/common/location.py
cloudmesh/common/logger.py
cloudmesh/common/network.py
cloudmesh/common/parameter.py
cloudmesh/common/prettytable.py
cloudmesh/common/security.py
cloudmesh/common/shlex.py
cloudmesh/common/strdb.py
cloudmesh/common/sudo.py
cloudmesh/common/systeminfo.py
cloudmesh/common/todo.py
cloudmesh/common/util.py
cloudmesh/common/variables.py
cloudmesh/common/wifi.py
cloudmesh/common/bin/__init__.py
cloudmesh/common/bin/create-conda.sh
cloudmesh/common/bin/win-setup.bat
cloudmesh/common/run/__init__.py
cloudmesh/common/run/background.py
cloudmesh/common/run/file.py
cloudmesh/common/run/subprocess.py
cloudmesh/common/ssh/__init__.py
cloudmesh/common/ssh/authorized_keys.py
cloudmesh/common/ssh/encrypt.py
cloudmesh/common/ssh/ssh_config.py
cloudmesh_common-5.0.64.dist-info/licenses/AUTHORS
cloudmesh_common-5.0.64.dist-info/licenses/LICENSE
cloudmesh_common-5.0.64.dist-info/METADATA
cloudmesh_common-5.0.64.dist-info/WHEEL
cloudmesh_common-5.0.64.dist-info/top_level.txt
cloudmesh_common-5.0.64.dist-info/RECORD
